MANIFEST.in
hello_pro.pyd
setup.py
hello_ofi5.egg-info/PKG-INFO
hello_ofi5.egg-info/SOURCES.txt
hello_ofi5.egg-info/dependency_links.txt
hello_ofi5.egg-info/top_level.txt