Metadata-Version: 1.1
Name: hello-ofi5
Version: 0.0.1
Summary: A basic hello package
Home-page: UNKNOWN
Author: Andrew (Florian Dedov)
Author-email: <ablasi@bettercare.es>
License: UNKNOWN
Keywords: python,video,stream,video stream,camera stream,sockets
Platform: UNKNOWN
Classifier: Development Status :: 1 - Planning
Classifier: Intended Audience :: Developers
Classifier: Programming Language :: Python :: 3
Classifier: Operating System :: Unix
Classifier: Operating System :: MacOS :: MacOS X
Classifier: Operating System :: Microsoft :: Windows
